autoinstaller.py
setup.py
autoinstaller.egg-info/PKG-INFO
autoinstaller.egg-info/SOURCES.txt
autoinstaller.egg-info/dependency_links.txt
autoinstaller.egg-info/top_level.txt