Metadata-Version: 1.0
Name: autoinstaller
Version: 0.1
Summary: A library that automatically imports from Pypi everything you try import
Home-page: https://github.com/mdipierro/autoinstaller
Author: Massimo DiPierro
Author-email: massimo.dipierro@gmail.com
License: BSD
Keywords: package management
Platform: UNKNOWN
